{
  "coord": {
    "lon": -49.4858,
    "lat": -28.9347
  },
  "weather": [
    {
      "id": 802,
      "main": "Clouds",
      "description": "scattered clouds",
      "icon": "03d"
    }
  ],
  "base": "stations",
  "main": {
    "temp": 20.9,
    "feels_like": 21,
    "temp_min": 20.9,
    "temp_max": 20.9,
    "pressure": 1017,
    "humidity": 75,
    "sea_level": 1017,
    "grnd_level": 1017
  },
  "visibility": 10000,
  "wind": {
    "speed": 3.55,
    "deg": 146,
    "gust": 2.98
  },
  "clouds": {
    "all": 30
  },
  "dt": 1780853054,
  "sys": {
    "country": "BR",
    "sunrise": 1780826781,
    "sunset": 1780864051
  },
  "timezone": -10800,
  "id": 3471772,
  "name": "Araranguá",
  "cod": 200,
  "_last_updated_utc": "2026-06-07T17:24:14.095Z"
}