{
  "coord": {
    "lon": -49.4858,
    "lat": -28.9347
  },
  "weather": [
    {
      "id": 800,
      "main": "Clear",
      "description": "clear sky",
      "icon": "01n"
    }
  ],
  "base": "stations",
  "main": {
    "temp": 8.75,
    "feels_like": 8.3,
    "temp_min": 8.75,
    "temp_max": 8.75,
    "pressure": 1019,
    "humidity": 77,
    "sea_level": 1019,
    "grnd_level": 1019
  },
  "visibility": 10000,
  "wind": {
    "speed": 1.43,
    "deg": 336,
    "gust": 1.57
  },
  "clouds": {
    "all": 0
  },
  "dt": 1783582996,
  "sys": {
    "country": "BR",
    "sunrise": 1783591878,
    "sunset": 1783629276
  },
  "timezone": -10800,
  "id": 3471772,
  "name": "Araranguá",
  "cod": 200,
  "_last_updated_utc": "2026-07-09T07:43:16.634Z"
}