{
  "coord": {
    "lon": -49.4858,
    "lat": -28.9347
  },
  "weather": [
    {
      "id": 803,
      "main": "Clouds",
      "description": "broken clouds",
      "icon": "04n"
    }
  ],
  "base": "stations",
  "main": {
    "temp": 22.89,
    "feels_like": 23.4,
    "temp_min": 22.89,
    "temp_max": 22.89,
    "pressure": 1012,
    "humidity": 83,
    "sea_level": 1012,
    "grnd_level": 1012
  },
  "visibility": 10000,
  "wind": {
    "speed": 2.04,
    "deg": 306,
    "gust": 3.07
  },
  "clouds": {
    "all": 61
  },
  "dt": 1775169545,
  "sys": {
    "country": "BR",
    "sunrise": 1775122111,
    "sunset": 1775164451
  },
  "timezone": -10800,
  "id": 3471772,
  "name": "Araranguá",
  "cod": 200,
  "_last_updated_utc": "2026-04-02T22:39:05.128Z"
}