{
  "coord": {
    "lon": -49.4858,
    "lat": -28.9347
  },
  "weather": [
    {
      "id": 500,
      "main": "Rain",
      "description": "light rain",
      "icon": "10d"
    }
  ],
  "base": "stations",
  "main": {
    "temp": 13.44,
    "feels_like": 13.37,
    "temp_min": 13.44,
    "temp_max": 13.44,
    "pressure": 1021,
    "humidity": 97,
    "sea_level": 1021,
    "grnd_level": 1020
  },
  "visibility": 10000,
  "wind": {
    "speed": 1.53,
    "deg": 243,
    "gust": 2.45
  },
  "rain": {
    "1h": 0.15
  },
  "clouds": {
    "all": 100
  },
  "dt": 1782821704,
  "sys": {
    "country": "BR",
    "sunrise": 1782814317,
    "sunset": 1782851457
  },
  "timezone": -10800,
  "id": 3471772,
  "name": "Araranguá",
  "cod": 200,
  "_last_updated_utc": "2026-06-30T12:15:04.947Z"
}