{
  "coord": {
    "lon": -49.4858,
    "lat": -28.9347
  },
  "weather": [
    {
      "id": 500,
      "main": "Rain",
      "description": "light rain",
      "icon": "10d"
    }
  ],
  "base": "stations",
  "main": {
    "temp": 17.89,
    "feels_like": 18.32,
    "temp_min": 17.89,
    "temp_max": 17.89,
    "pressure": 1014,
    "humidity": 99,
    "sea_level": 1014,
    "grnd_level": 1013
  },
  "visibility": 4071,
  "wind": {
    "speed": 3.02,
    "deg": 181,
    "gust": 6.17
  },
  "rain": {
    "1h": 0.38
  },
  "clouds": {
    "all": 100
  },
  "dt": 1782675519,
  "sys": {
    "country": "BR",
    "sunrise": 1782641512,
    "sunset": 1782678618
  },
  "timezone": -10800,
  "id": 3471772,
  "name": "Araranguá",
  "cod": 200,
  "_last_updated_utc": "2026-06-28T19:38:39.562Z"
}