{
  "coord": {
    "lon": -49.4858,
    "lat": -28.9347
  },
  "weather": [
    {
      "id": 804,
      "main": "Clouds",
      "description": "overcast clouds",
      "icon": "04d"
    }
  ],
  "base": "stations",
  "main": {
    "temp": 18.01,
    "feels_like": 17.54,
    "temp_min": 18.01,
    "temp_max": 18.01,
    "pressure": 1017,
    "humidity": 64,
    "sea_level": 1017,
    "grnd_level": 1016
  },
  "visibility": 10000,
  "wind": {
    "speed": 1.7,
    "deg": 118,
    "gust": 1.19
  },
  "clouds": {
    "all": 100
  },
  "dt": 1781106744,
  "sys": {
    "country": "BR",
    "sunrise": 1781086055,
    "sunset": 1781123244
  },
  "timezone": -10800,
  "id": 3471772,
  "name": "Araranguá",
  "cod": 200,
  "_last_updated_utc": "2026-06-10T15:52:24.824Z"
}