{
  "coord": {
    "lon": -49.4858,
    "lat": -28.9347
  },
  "weather": [
    {
      "id": 802,
      "main": "Clouds",
      "description": "scattered clouds",
      "icon": "03d"
    }
  ],
  "base": "stations",
  "main": {
    "temp": 21.56,
    "feels_like": 21.47,
    "temp_min": 21.56,
    "temp_max": 21.56,
    "pressure": 1026,
    "humidity": 65,
    "sea_level": 1026,
    "grnd_level": 1026
  },
  "visibility": 10000,
  "wind": {
    "speed": 4.07,
    "deg": 95,
    "gust": 4.76
  },
  "clouds": {
    "all": 48
  },
  "dt": 1780506108,
  "sys": {
    "country": "BR",
    "sunrise": 1780481072,
    "sunset": 1780518479
  },
  "timezone": -10800,
  "id": 3471772,
  "name": "Araranguá",
  "cod": 200,
  "_last_updated_utc": "2026-06-03T17:01:48.652Z"
}